pretix_limit_phone_country/__init__.py
pretix_limit_phone_country/signals.py
pretix_limit_phone_country/locale/de/LC_MESSAGES/django.po
pretix_limit_phone_country/locale/de_Informal/.gitkeep
pretix_limit_phone_country/locale/de_Informal/LC_MESSAGES/django.po
pretix_limit_phone_country/static/pretix_limit_phone_country/.gitkeep
pretix_limit_phone_country/templates/pretix_limit_phone_country/.gitkeep
pretix_limit_phone_country-0.9.0.dist-info/LICENSE
pretix_limit_phone_country-0.9.0.dist-info/METADATA
pretix_limit_phone_country-0.9.0.dist-info/WHEEL
pretix_limit_phone_country-0.9.0.dist-info/entry_points.txt
pretix_limit_phone_country-0.9.0.dist-info/top_level.txt
pretix_limit_phone_country-0.9.0.dist-info/RECORD
