Metadata-Version: 2.1
Name: pretix-limit-phone-country
Version: 0.9.0
Summary: Limit the available phone number country code in pretix phone number questions. Caution! Applies to the whole server!
Home-page: https://github.com/rixx/pretix-limit-phone-country
Author: Tobias Kunze
Author-email: r@rixx.de
License: Apache
Platform: UNKNOWN
